polars_qt-0.1.28.dist-info/METADATA
polars_qt-0.1.28.dist-info/WHEEL
polars_qt-0.1.28.dist-info/licenses/LICENSE
polars_qt/__init__.py
polars_qt/equity.py
polars_qt/funcs.py
polars_qt/polars_qt.pyd
polars_qt/qt.py
polars_qt/strategy.py
polars_qt/utils.py
polars_qt-0.1.28.dist-info/RECORD
